dist/ka_ut_obj-2023.3.1.tar.gz
ka_ut_obj/__init__.py
ka_ut_obj/__version__.py
ka_ut_obj/aoa.py
ka_ut_obj/aod.py
ka_ut_obj/aoo.py
ka_ut_obj/aos.py
ka_ut_obj/args.py
ka_ut_obj/arr.py
ka_ut_obj/arrs.py
ka_ut_obj/d2v.py
ka_ut_obj/d3v.py
ka_ut_obj/dic.py
ka_ut_obj/doa.py
ka_ut_obj/dod.py
ka_ut_obj/doo.py
ka_ut_obj/obj.py
ka_ut_obj/py.typed
ka_ut_obj/setdic.py
ka_ut_obj/str.py
ka_ut_obj/data/__init__.py
ka_ut_obj/data/log.main.tenant.yml
ka_ut_obj/data/log.yml
ka_ut_obj-2023.3.1.dist-info/LICENSE.txt
ka_ut_obj-2023.3.1.dist-info/METADATA
ka_ut_obj-2023.3.1.dist-info/WHEEL
ka_ut_obj-2023.3.1.dist-info/top_level.txt
ka_ut_obj-2023.3.1.dist-info/RECORD
